flureenjs/core/__init__.py
flureenjs/core/py.typed
flureenjs/core/_jsii/__init__.py
flureenjs/core/_jsii/fluree-jsii@1.0.3.jsii.tgz
flureenjs.core-1.0.3.dist-info/LICENSE
flureenjs.core-1.0.3.dist-info/METADATA
flureenjs.core-1.0.3.dist-info/WHEEL
flureenjs.core-1.0.3.dist-info/top_level.txt
flureenjs.core-1.0.3.dist-info/RECORD
