Metadata-Version: 2.1
Name: flureenjs.core
Version: 1.0.3
Summary: PoC app to try to generate libraries from flureenjs
Home-page: https://github.com/fluree/fluree-jsii.git
Author: Jacob Parsell<jparsell@flur.ee>
License: ISC
Project-URL: Source, https://github.com/fluree/fluree-jsii.git
Platform: UNKNOWN
Classifier: Intended Audience :: Developers
Classifier: Operating System :: OS Independent
Classifier: Programming Language :: JavaScript
Classifier: Programming Language :: Python :: 3 :: Only
Classifier: Programming Language :: Python :: 3.6
Classifier: Programming Language :: Python :: 3.7
Classifier: Programming Language :: Python :: 3.8
Classifier: Programming Language :: Python :: 3.9
Classifier: Typing :: Typed
Classifier: Development Status :: 4 - Beta
Classifier: License :: OSI Approved
Requires-Python: >=3.6
Requires-Dist: jsii (<2.0.0,>=1.47.0)
Requires-Dist: publication (>=0.0.3)
